{"type": "FeatureCollection", "features": [{"type": "Feature", "properties": {"start": "Geispolsheim", "stop_name": "Geispolsheim", "type": "Gare s\u00e9lectionn\u00e9e", "iconstarte": "Icon2"}, "geometry": {"type": "Point", "coordinates": [7.684358, 48.519052]}}, {"type": "Feature", "properties": {"start": "Geispolsheim", "stop_name": "S\u00e9lestat", "type": "Gare accessible", "icone": "TER"}, "geometry": {"type": "Point", "coordinates": [7.443157, 48.259824]}}, {"type": "Feature", "properties": {"start": "Geispolsheim", "stop_name": "Ebersheim", "type": "Gare accessible", "icone": "TER"}, "geometry": {"type": "Point", "coordinates": [7.494537, 48.310048]}}, {"type": "Feature", "properties": {"start": "Geispolsheim", "stop_name": "Kogenheim", "type": "Gare accessible", "icone": "TER"}, "geometry": {"type": "Point", "coordinates": [7.535288, 48.33879]}}, {"type": "Feature", "properties": {"start": "Geispolsheim", "stop_name": "Benfeld", "type": "Gare accessible", "icone": "TER"}, "geometry": {"type": "Point", "coordinates": [7.583866, 48.374069]}}, {"type": "Feature", "properties": {"start": "Geispolsheim", "stop_name": "Matzenheim", "type": "Gare accessible", "icone": "TER"}, "geometry": {"type": "Point", "coordinates": [7.619595, 48.398722]}}, {"type": "Feature", "properties": {"start": "Geispolsheim", "stop_name": "Erstein", "type": "Gare accessible", "icone": "TER"}, "geometry": {"type": "Point", "coordinates": [7.638701, 48.422982]}}, {"type": "Feature", "properties": {"start": "Geispolsheim", "stop_name": "Limersheim", "type": "Gare accessible", "icone": "TER"}, "geometry": {"type": "Point", "coordinates": [7.660306, 48.461592]}}, {"type": "Feature", "properties": {"start": "Geispolsheim", "stop_name": "Fegersheim - Lipsheim", "type": "Gare accessible", "icone": "TER"}, "geometry": {"type": "Point", "coordinates": [7.672481, 48.490589]}}, {"type": "Feature", "properties": {"start": "Geispolsheim", "stop_name": "Graffenstaden", "type": "Gare accessible", "icone": "TER"}, "geometry": {"type": "Point", "coordinates": [7.689236, 48.532788]}}, {"type": "Feature", "properties": {"start": "Geispolsheim", "stop_name": "Strasbourg", "type": "Gare accessible", "icone": "TER"}, "geometry": {"type": "Point", "coordinates": [7.734793, 48.584532]}}, {"type": "Feature", "properties": {"start": "Geispolsheim", "stop_name": "Colmar", "type": "Gare accessible", "icone": "TER"}, "geometry": {"type": "Point", "coordinates": [7.347756, 48.073527]}}, {"type": "Feature", "properties": {"start": "Geispolsheim", "stop_name": "Rouffach", "type": "Gare accessible", "icone": "TER"}, "geometry": {"type": "Point", "coordinates": [7.312529, 47.960188]}}, {"type": "Feature", "properties": {"start": "Geispolsheim", "stop_name": "Merxheim", "type": "Gare accessible", "icone": "TER"}, "geometry": {"type": "Point", "coordinates": [7.302333, 47.913189]}}, {"type": "Feature", "properties": {"start": "Geispolsheim", "stop_name": "Raedersheim", "type": "Gare accessible", "icone": "TER"}, "geometry": {"type": "Point", "coordinates": [7.284047, 47.886906]}}, {"type": "Feature", "properties": {"start": "Geispolsheim", "stop_name": "Bollwiller", "type": "Gare accessible", "icone": "TER"}, "geometry": {"type": "Point", "coordinates": [7.26718, 47.856969]}}, {"type": "Feature", "properties": {"start": "Geispolsheim", "stop_name": "Staffelfelden", "type": "Gare accessible", "icone": "TER"}, "geometry": {"type": "Point", "coordinates": [7.265018, 47.827618]}}, {"type": "Feature", "properties": {"start": "Geispolsheim", "stop_name": "Mulhouse Dornach", "type": "Gare accessible", "icone": "TER"}, "geometry": {"type": "Point", "coordinates": [7.308543, 47.746987]}}, {"type": "Feature", "properties": {"start": "Geispolsheim", "stop_name": "Mulhouse", "type": "Gare accessible", "icone": "TER"}, "geometry": {"type": "Point", "coordinates": [7.34316, 47.742691]}}]}