{"type": "FeatureCollection", "features": [{"type": "Feature", "properties": {"stop_name": "Goderville", "type": "Gare s\u00e9lectionn\u00e9e", "icone": "Icon2"}, "geometry": {"type": "Point", "coordinates": [0.367785, 49.645581]}}, {"type": "Feature", "properties": {"stop_name": "F\u00e9camp", "type": "Gare accessible", "icone": "Icon1"}, "geometry": {"type": "Point", "coordinates": [0.375287, 49.759277000000004]}}, {"type": "Feature", "properties": {"stop_name": "Br\u00e9aut\u00e9 - Beuzeville", "type": "Gare accessible", "icone": "Icon1"}, "geometry": {"type": "Point", "coordinates": [0.417489, 49.603396000000004]}}]}