{"type": "FeatureCollection", "features": [{"type": "Feature", "properties": {"stop_name": "Montlucon", "type": "Gare s\u00e9lectionn\u00e9e"}, "geometry": {"type": "Point", "coordinates": [2.60962, 46.338253]}}, {"type": "Feature", "properties": {"stop_name": "Riom - Ch\u00e2tel-Guyon", "type": "Gare accessible"}, "geometry": {"type": "Point", "coordinates": [3.120498, 45.889965000000004]}}, {"type": "Feature", "properties": {"stop_name": "Aigueperse", "type": "Gare accessible"}, "geometry": {"type": "Point", "coordinates": [3.197912, 46.014869]}}, {"type": "Feature", "properties": {"stop_name": "Gannat", "type": "Gare accessible"}, "geometry": {"type": "Point", "coordinates": [3.204773, 46.097592]}}, {"type": "Feature", "properties": {"stop_name": "Lapeyrouse", "type": "Gare accessible"}, "geometry": {"type": "Point", "coordinates": [2.893315, 46.226759]}}, {"type": "Feature", "properties": {"stop_name": "Commentry", "type": "Gare accessible"}, "geometry": {"type": "Point", "coordinates": [2.739938, 46.295105]}}, {"type": "Feature", "properties": {"stop_name": "Montlu\u00e7on", "type": "Gare accessible"}, "geometry": {"type": "Point", "coordinates": [2.596159, 46.338101]}}]}