{"type": "FeatureCollection", "features": [{"type": "Feature", "properties": {"stop_name": "Pont-de-Buis", "type": "Gare s\u00e9lectionn\u00e9e", "icone": "Icon2"}, "geometry": {"type": "Point", "coordinates": [-4.086123000000001, 48.254402]}}, {"type": "Feature", "properties": {"stop_name": "Quimper", "type": "Gare accessible", "icone": "Icon1"}, "geometry": {"type": "Point", "coordinates": [-4.092103, 47.994455]}}, {"type": "Feature", "properties": {"stop_name": "Ch\u00e2teaulin", "type": "Gare accessible", "icone": "Icon1"}, "geometry": {"type": "Point", "coordinates": [-4.094308, 48.201603000000006]}}, {"type": "Feature", "properties": {"stop_name": "Dirinon", "type": "Gare accessible", "icone": "Icon1"}, "geometry": {"type": "Point", "coordinates": [-4.285355, 48.392666999999996]}}, {"type": "Feature", "properties": {"stop_name": "Landerneau", "type": "Gare accessible", "icone": "Icon1"}, "geometry": {"type": "Point", "coordinates": [-4.256528, 48.453571999999994]}}, {"type": "Feature", "properties": {"stop_name": "Brest", "type": "Gare accessible", "icone": "Icon1"}, "geometry": {"type": "Point", "coordinates": [-4.480306, 48.38762]}}]}