{"type": "FeatureCollection", "features": [{"type": "Feature", "properties": {"stop_name": "Villeneuve-sur-Allier Centre", "type": "Gare s\u00e9lectionn\u00e9e"}, "geometry": {"type": "Point", "coordinates": [3.247131, 46.660457]}}, {"type": "Feature", "properties": {"stop_name": "Nevers", "type": "Gare accessible"}, "geometry": {"type": "Point", "coordinates": [3.150743, 46.987282]}}, {"type": "Feature", "properties": {"stop_name": "Saincaize", "type": "Gare accessible"}, "geometry": {"type": "Point", "coordinates": [3.071937, 46.931405]}}, {"type": "Feature", "properties": {"stop_name": "Saint-Pierre-le-Mo\u00fbtier", "type": "Gare accessible"}, "geometry": {"type": "Point", "coordinates": [3.111738, 46.793278]}}, {"type": "Feature", "properties": {"stop_name": "Chantenay-Saint-Imbert Bourg", "type": "Gare accessible"}, "geometry": {"type": "Point", "coordinates": [3.183146, 46.733098]}}, {"type": "Feature", "properties": {"stop_name": "Chantenay-Saint-Imbert", "type": "Gare accessible"}, "geometry": {"type": "Point", "coordinates": [3.171472, 46.728556]}}, {"type": "Feature", "properties": {"stop_name": "Moulins sur Allier", "type": "Gare accessible"}, "geometry": {"type": "Point", "coordinates": [3.338782, 46.561394]}}]}